bunnets/__init__.py
bunnets/error.py
bunnets/func.py
bunnets/py.typed
bunnets/typedefs.py
bunnets/typehintlib.py
bunnets/test/test_coercion.py
bunnets/test/test_decorators.py
bunnets/test/test_func.py
bunnets/test/test_types.py
bunnets-0.9.1.dist-info/METADATA
bunnets-0.9.1.dist-info/WHEEL
bunnets-0.9.1.dist-info/top_level.txt
bunnets-0.9.1.dist-info/RECORD
